Metadata-Version: 1.0
Name: distributions-mf
Version: 0.2
Summary: A package created as a nanodegree exercise from Machine Learning Engineer course.
Home-page: UNKNOWN
Author: UNKNOWN
Author-email: UNKNOWN
License: UNKNOWN
Platform: UNKNOWN
